.gitignore
LICENSE
README.md
setup.py
bin/library_count_sgrna
bin/library_count_sgrna_with_barcode
bin/zfc
doc/al.bib
doc/algorithm.tex
doc/zfc_algorithm.svg
doc/zfc_algorithm_new.png
doc/zfc_algorithm_new.svg
doc/zfc_card.png
doc/zfc_card.svg
doc/zfc_logo.png
doc/zfclogo.svg
doc/zfclogo_design.svg
doc/zfclogo_white.svg
zfc/__init__.py
zfc/plot.py
zfc/programio.py
zfc/statsfunc.py
zfc/zfoldchange.py
zfc.egg-info/PKG-INFO
zfc.egg-info/SOURCES.txt
zfc.egg-info/dependency_links.txt
zfc.egg-info/not-zip-safe
zfc.egg-info/requires.txt
zfc.egg-info/top_level.txt