Metadata-Version: 2.1
Name: zfc
Version: 0.1.7
Summary: The zfc software is used for analysis of counts data.
Home-page: https://github.com/wolfsonliu/zfc
Author: Zhiheng Liu
Author-email: zhiheng.liu@pku.edu.cn
License: GPL
Platform: UNKNOWN
Classifier: Development Status :: 1 - Planning
Classifier: Programming Language :: Python :: 3
Classifier: License :: OSI Approved :: GNU General Public License v3 or later (GPLv3+)
License-File: LICENSE
